loozr_near_sdk/__init__.py
loozr_near_sdk/account.py
loozr_near_sdk/creator_coin.py
loozr_near_sdk/utils/__init__.py
loozr_near_sdk/utils/base.py
loozr_near_sdk/utils/constants.py
loozr_near_sdk/utils/exceptions.py
loozr_near_sdk/utils/format.py
loozr_near_sdk-0.0.6.dist-info/METADATA
loozr_near_sdk-0.0.6.dist-info/WHEEL
loozr_near_sdk-0.0.6.dist-info/top_level.txt
loozr_near_sdk-0.0.6.dist-info/RECORD
