Metadata-Version: 2.1
Name: loozr-near-sdk
Version: 0.0.6
Home-page: https://github.com/Loozr-Protocol/loozr-near-py
Author: Loozr Inc
License: MIT
Classifier: Development Status :: 3 - Alpha
Classifier: Programming Language :: Python :: 3
Classifier: License :: OSI Approved :: MIT License
Classifier: Operating System :: OS Independent
Requires-Dist: lzr-near-api-py
